py_noodle-0.1.1.dist-info/licenses/LICENSE
pynoodle/__init__.py
pynoodle/config.py
pynoodle/hooks.py
pynoodle/noodle.py
pynoodle/scenario.py
pynoodle/c2p/__init__.py
pynoodle/endpoints/__init__.py
pynoodle/endpoints/dependencies.py
pynoodle/endpoints/proxy.py
pynoodle/endpoints/scene.py
pynoodle/scene/__init__.py
pynoodle/scene/lock.py
pynoodle/scene/scene_node.py
pynoodle/scene/server_template.py
pynoodle/scene/treeger.py
pynoodle/schemas/__init__.py
pynoodle/schemas/dependencies.py
pynoodle/schemas/lock.py
pynoodle/schemas/scenario.py
pynoodle/schemas/scene.py
py_noodle-0.1.1.dist-info/METADATA
py_noodle-0.1.1.dist-info/WHEEL
py_noodle-0.1.1.dist-info/top_level.txt
py_noodle-0.1.1.dist-info/RECORD
