Metadata-Version: 2.4
Name: py-noodle
Version: 0.1.1
Summary: Node-oriented open data linking environment powered by C-Two.
Requires-Python: >=3.10
License-File: LICENSE
Requires-Dist: c-two>=0.2.5
Requires-Dist: fastapi>=0.116.1
Requires-Dist: pyyaml>=6.0.2
Dynamic: license-file
